<?xml version="1.0" encoding="UTF-8"?>
<template name="GetPolo1ObraStatesSequenceTemplate" xmlns="http://ws.apache.org/ns/synapse">
    <parameter name="obra"/>
    <sequence>
        <log description="Start Get Polo1 Obra States Sequence" level="custom">
            <property name="message" value="Start getting Polo1 obra states sequence"/>
        </log>
        <property description="Store obra as uri property" expression="$func:obra" name="uri.var.obra" scope="default" type="STRING"/>
        <call>
            <endpoint>
                <http method="get" statistics="enable" trace="enable" uri-template="http://localhost:8280/acervobiblioteca/polos/polo1/obras/{uri.var.obra}">
                    <suspendOnFailure>
                        <initialDuration>-1</initialDuration>
                        <progressionFactor>-1</progressionFactor>
                        <maximumDuration>0</maximumDuration>
                    </suspendOnFailure>
                    <markForSuspension>
                        <retriesBeforeSuspension>0</retriesBeforeSuspension>
                    </markForSuspension>
                </http>
            </endpoint>
        </call>
        <datamapper config="gov:datamapper/MapPoloObraStatesPropertyToPoloObraStates.dmc" description="MapPoloObraStatesPropertyToPoloObraStates" inputSchema="gov:datamapper/MapPoloObraStatesPropertyToPoloObraStates_inputSchema.json" inputType="JSON" outputSchema="gov:datamapper/MapPoloObraStatesPropertyToPoloObraStates_outputSchema.json" outputType="JSON" xsltStyleSheet="gov:datamapper/MapPoloObraStatesPropertyToPoloObraStates_xsltStyleSheet.xml"/>
        <log description="Finish Get Polo1 Obra States Sequence" level="custom">
            <property name="message" value="Finished get polo1 obra states..."/>
        </log>
    </sequence>
</template>
